.gitignore
.travis.yml
CONTRIBUTING.md
LICENSE.txt
MANIFEST.in
README.rst
bootstrap.sh
setup.py
simp_le.py
venv.sh
docker/Dockerfile
docker/README.md
docker/entrypoint.sh
docker/hooks/build
docker/hooks/post_push
docker/hooks/push
pyi/.gitignore
pyi/Makefile
pyi/README.md
pyi/entrypoints.py
pyi/requirements.txt
pyi/rthook-entrypoints.py
pyi/simp_le.spec
simp_le_client.egg-info/PKG-INFO
simp_le_client.egg-info/SOURCES.txt
simp_le_client.egg-info/dependency_links.txt
simp_le_client.egg-info/entry_points.txt
simp_le_client.egg-info/requires.txt
simp_le_client.egg-info/top_level.txt
tests/install.sh
tests/test-suite.sh