Metadata-Version: 2.1
Name: simp-le-client
Version: 0.19.1
Summary: Simple Let's Encrypt Client
Home-page: https://github.com/zenhack/simp_le
Author: Ian Denhardt
Author-email: ian@zenhack.net
License: GPLv3
Platform: UNKNOWN
Classifier: Development Status :: 6 - Mature
Classifier: Environment :: Console
Classifier: Intended Audience :: System Administrators
Classifier: License :: OSI Approved :: GNU General Public License v3 (GPLv3)
Classifier: Operating System :: POSIX :: Linux
Classifier: Programming Language :: Python
Classifier: Programming Language :: Python :: 3
Classifier: Programming Language :: Python :: 3.5
Classifier: Programming Language :: Python :: 3.6
Classifier: Programming Language :: Python :: 3.7
Classifier: Topic :: Internet :: WWW/HTTP
Classifier: Topic :: Security
Classifier: Topic :: System :: Installation/Setup
Classifier: Topic :: System :: Networking
Classifier: Topic :: System :: Systems Administration
Classifier: Topic :: Utilities
Provides-Extra: tests
License-File: LICENSE.txt
